ai_datastream/__init__.py
ai_datastream/agent/__init__.py
ai_datastream/agent/langgraph/README.md
ai_datastream/agent/langgraph/__init__.py
ai_datastream/agent/langgraph/message_parser.py
ai_datastream/agent/langgraph/stream_converter.py
ai_datastream/agent/langgraph/streamer.py
ai_datastream/api/__init__.py
ai_datastream/api/fastapi/README.md
ai_datastream/api/fastapi/__init__.py
ai_datastream/api/fastapi/response.py
ai_datastream/api/fastapi/types.py
ai_datastream/consts.py
ai_datastream/messages.py
ai_datastream/stream_parts.py
ai_datastream/streamer.py
ai_datastream-0.1.1.dist-info/LICENSE
ai_datastream-0.1.1.dist-info/METADATA
ai_datastream-0.1.1.dist-info/WHEEL
ai_datastream-0.1.1.dist-info/RECORD
